{
  "slug": "day-38-juliano-and-marcozi",
  "title": "Juliano and Marcozi",
  "part": "Brazil",
  "day": "Day 38",
  "pageStart": 0,
  "pageEnd": 0,
  "order": 34,
  "source": "Book_Meet on the Road (final edition).docx",
  "blocks": [
    [
      "As the morning sun shone into the room, I noticed two faces I hadn't seen the night before -- Juliano and Marcozi, my new roommates. Their friendly chatter and shared enthusiasm for the beach led us on an impromptu outing together. Juliano, who was 28 years old, informed us that his mother's house was nearby, which made me curious why he chose to stay in the Albergue. He had been working in Porto Alegre and arrived yesterday with plans to travel to São Paulo soon. Juliano was lively and expressive, frequently using hand gestures and speaking slowly to ensure I understood him. Marcozi, on the other hand, a decade older, was on a personal journey after a torturous life-changing divorce. He spoke softly about his two kids, hinting at the weight of memories."
    ],
    [
      "On our way to the beach, the trip took a fortunate turn when we ran into",
      "one of Juliano's friends, who drove us there. The car ride spared us a",
      "long walk. But before reaching the beach, we took a detour to Juliano's",
      "family home. His mother, with eyes that spoke volumes of concern, seemed",
      "a tad wary of my adventures. I showed her my new passport in hopes of",
      "easing her concerns. Her gentle smile told me it worked."
    ],
    [
      "The beach, pristine and almost untouched, was a haven. Apart from a few",
      "distant figures, the place exuded calm. Juliano couldn't resist the",
      "ocean's call, rushing and diving in with childlike exhilaration. The",
      "waves, though fierce, only added to the fun. After the splash and",
      "laughter, we lounged, lost in the beauty on the horizon and the soothing",
      "rhythm of the waves."
    ],
    [
      "Back at Juliano's, he introduced me to Capoeira in their garden. This",
      "Brazilian martial art, blending dance and martial moves, was a",
      "revelation. Matching his steps was both stimulating and challenging. Our",
      "playful bouts left us spent, laughing under the sun. Lunchtime brought",
      "us back indoors. The delightful aroma hinted at a sumptuous meal. As we",
      "relished each bite, I caught Juliano's mother watching us, her eyes",
      "reflecting contentment. My heart was filled with memories of the",
      "wonderful coincidences and unexpected pleasures that come with travel."
    ],
    [
      "A Day of Contrasts"
    ],
    [
      "As we parted ways from Juliano's mother, her warm embrace lingered,",
      "contrasting with the chilly evening air that awaited us. The path back",
      "to Araranguá was draped in silence, every step carrying the weight of",
      "the day's contrasts. Out of the blue, Juliano asked if I wanted to",
      "smoke marijuana. I declined without hesitation, and he and Marcozi",
      "slipped into the brush to smoke. When they returned, Juliano no longer",
      "had the cheerful face from earlier. His speech had grown slurred and",
      "unclear, and his eyes stared out with an angry intensity."
    ],
    [
      "Then he hurriedly borrowed ten reais from me, promising to pay it back",
      "at the shelter. Against my hopes, he bought more marijuana. Still not",
      "satisfied, he tried to sell me the mate tea tools his mother had given",
      "him, and when I refused, he disappeared, perhaps to sell them elsewhere.",
      "Marcozi and I waited a long time, but Juliano never came back. Marcozi",
      "told me Juliano was also under the influence of heroin. My heart ached.",
      "I blamed myself for being unable to help him, and even more because I",
      "had lent him money for the drugs. We had become friends that day, yet I",
      "was still only an outsider, able to watch but not interfere in their lives."
    ],
    [
      "Our way back turned into a cavalcade of failed hitchhiking attempts. As",
      "darkness fell, Marcozi paused, seemingly tired from the walk, and",
      "offered me a glass of cachaça to ward off the evening chill. We",
      "purchased a bottle for two reais, a potent liquor. He informed me that",
      "cachaça is immensely popular in Brazil. We finished our drinks and",
      "continued our journey."
    ],
    [
      "Reaching the outskirts of Araranguá, houses began to appear. Marcozi",
      "started asking for alms door-to-door and eventually handed me a one-real",
      "note, likely repaying me for the earlier cachaça. I bluntly refused the",
      "money, insisting we just keep walking. Watching him beg and point at me",
      "while explaining my situation made me uncomfortable."
    ],
    [
      "He attempted to explain something. Although I didn't fully grasp his",
      "words, one thing was clear: this is Brazil, where people give without",
      "expecting anything in return."
    ],
    [
      "He kept asking for help as we walked. I tried to hurry him along but",
      "eventually gave up and walked ahead, waiting for him to catch up before",
      "moving on again."
    ],
    [
      "Later, he brought four reais. I declined the money again, and we used it",
      "to buy a pack of cigarettes."
    ],
    [
      "I felt like a mere spectator, unable to engage in their way of life,",
      "only to observe. However, watching him was enlightening. He asked for",
      "help unabashedly, and many readily provided assistance. Observing the",
      "helpers, I pondered the lifestyle and generosity of the local people."
    ],
    [
      "It was already past nine by the time we reached Albergue Sao Marcos, and the door was firmly shut --- the shelter admitted newcomers only between six and nine in the evening. The caretaker met us with a stern yet empathetic gaze; we were late, yet his eyes read the weariness on our faces, and he let us in. Inside, Juliano's absence loomed like a specter, yet the warmth of the soup seemed to fill the void momentarily. As I lay in bed, the day's events danced in the shadows on the ceiling. A kaleidoscope of contrasts, camaraderie intertwined with desperation, joy overshadowed by despair. Here I was, far away from home, amid strangers turned companions. Yet, as the night shrouded the room, it dawned on me that while our paths had intertwined, our battles were our own. I was but a spectator in their fight against their own shadows. And sometimes, that's all one can be in the complex dance of life and survival. As sleep enveloped me, my thoughts echoed the silent whispers of introspection, the gentle hum of reality, and the quiet acceptance of the diverging paths ahead."
    ]
  ],
  "media": [
    {
      "afterBlock": 2,
      "images": [
        {
          "src": "/images/book-reader/gil-eseo-mannada/sketches/juliano-and-marcoji-sketch.webp",
          "alt": "Meet On The Road Juliano and Marcozi beach hand sketch illustration",
          "width": 1536,
          "height": 1024
        }
      ]
    }
  ],
  "characterCount": 4795,
  "wordCount": 1006,
  "readTimeMinutes": 5
}
