{
  "bookId": "meet-on-the-road",
  "title": "Meet On The Road Online Edition",
  "description": "The complete English edition of Meet On The Road is available to read online for free.",
  "source": "Book_Meet on the Road (final edition).docx",
  "chapters": [
    {
      "slug": "day-01-lost",
      "title": "Lost",
      "part": "Argentina",
      "day": "Day 1",
      "pageStart": 0,
      "pageEnd": 0,
      "order": 1,
      "characterCount": 6026,
      "wordCount": 1249,
      "readTimeMinutes": 6
    },
    {
      "slug": "day-02-alone-yet-not-alone",
      "title": "Alone Yet Not Alone",
      "part": "Argentina",
      "day": "Day 2",
      "pageStart": 0,
      "pageEnd": 0,
      "order": 2,
      "characterCount": 2023,
      "wordCount": 410,
      "readTimeMinutes": 2
    },
    {
      "slug": "day-03-a-new-dawn",
      "title": "A New Dawn",
      "part": "Argentina",
      "day": "Day 3",
      "pageStart": 0,
      "pageEnd": 0,
      "order": 3,
      "characterCount": 1259,
      "wordCount": 258,
      "readTimeMinutes": 2
    },
    {
      "slug": "day-04-buenos-aires-whispers-embrace-the-journey-not-the-shortcut",
      "title": "Buenos Aires Whispers: Embrace the Journey, Not the Shortcut",
      "part": "Argentina",
      "day": "Day 4",
      "pageStart": 0,
      "pageEnd": 0,
      "order": 4,
      "characterCount": 1629,
      "wordCount": 327,
      "readTimeMinutes": 2
    },
    {
      "slug": "day-05-purpose",
      "title": "Purpose",
      "part": "Argentina",
      "day": "Day 5",
      "pageStart": 0,
      "pageEnd": 0,
      "order": 5,
      "characterCount": 6882,
      "wordCount": 1436,
      "readTimeMinutes": 7
    },
    {
      "slug": "day-06-a-step-forward",
      "title": "A Step Forward",
      "part": "Argentina",
      "day": "Day 6",
      "pageStart": 0,
      "pageEnd": 0,
      "order": 6,
      "characterCount": 2929,
      "wordCount": 617,
      "readTimeMinutes": 3
    },
    {
      "slug": "day-07-sincerity",
      "title": "Sincerity",
      "part": "Argentina",
      "day": "Day 7",
      "pageStart": 0,
      "pageEnd": 0,
      "order": 7,
      "characterCount": 2783,
      "wordCount": 597,
      "readTimeMinutes": 3
    },
    {
      "slug": "day-08-sol",
      "title": "SOL",
      "part": "Argentina",
      "day": "Day 8",
      "pageStart": 0,
      "pageEnd": 0,
      "order": 8,
      "characterCount": 1264,
      "wordCount": 263,
      "readTimeMinutes": 2
    },
    {
      "slug": "day-10-ready-to-roll",
      "title": "Ready to Roll",
      "part": "Argentina",
      "day": "Day 10",
      "pageStart": 0,
      "pageEnd": 0,
      "order": 9,
      "characterCount": 736,
      "wordCount": 151,
      "readTimeMinutes": 1
    },
    {
      "slug": "day-11-will",
      "title": "Will",
      "part": "Argentina",
      "day": "Day 11",
      "pageStart": 0,
      "pageEnd": 0,
      "order": 10,
      "characterCount": 1139,
      "wordCount": 242,
      "readTimeMinutes": 2
    },
    {
      "slug": "day-12-tango",
      "title": "Tango",
      "part": "Argentina",
      "day": "Day 12",
      "pageStart": 0,
      "pageEnd": 0,
      "order": 11,
      "characterCount": 1084,
      "wordCount": 233,
      "readTimeMinutes": 2
    },
    {
      "slug": "day-13-on-the-eve",
      "title": "On the Eve",
      "part": "Argentina",
      "day": "Day 13",
      "pageStart": 0,
      "pageEnd": 0,
      "order": 12,
      "characterCount": 1224,
      "wordCount": 246,
      "readTimeMinutes": 2
    },
    {
      "slug": "day-14-to-the-unknown",
      "title": "To the Unknown",
      "part": "Argentina",
      "day": "Day 14",
      "pageStart": 0,
      "pageEnd": 0,
      "order": 13,
      "characterCount": 3201,
      "wordCount": 666,
      "readTimeMinutes": 4
    },
    {
      "slug": "day-15-rosario",
      "title": "Rosario",
      "part": "Argentina",
      "day": "Day 15",
      "pageStart": 0,
      "pageEnd": 0,
      "order": 14,
      "characterCount": 5668,
      "wordCount": 1138,
      "readTimeMinutes": 6
    },
    {
      "slug": "day-16-on-the-street",
      "title": "On The Street",
      "part": "Argentina",
      "day": "Day 16",
      "pageStart": 0,
      "pageEnd": 0,
      "order": 15,
      "characterCount": 1901,
      "wordCount": 388,
      "readTimeMinutes": 2
    },
    {
      "slug": "day-17-detour",
      "title": "Detour",
      "part": "Argentina",
      "day": "Day 17",
      "pageStart": 0,
      "pageEnd": 0,
      "order": 16,
      "characterCount": 2278,
      "wordCount": 449,
      "readTimeMinutes": 3
    },
    {
      "slug": "day-19-immanuel",
      "title": "Immanuel",
      "part": "Argentina",
      "day": "Day 19",
      "pageStart": 0,
      "pageEnd": 0,
      "order": 17,
      "characterCount": 1249,
      "wordCount": 260,
      "readTimeMinutes": 2
    },
    {
      "slug": "day-21-bicycle",
      "title": "Bicycle",
      "part": "Argentina",
      "day": "Day 21",
      "pageStart": 0,
      "pageEnd": 0,
      "order": 18,
      "characterCount": 3980,
      "wordCount": 763,
      "readTimeMinutes": 4
    },
    {
      "slug": "day-22-hitchhiking",
      "title": "Hitchhiking",
      "part": "Argentina",
      "day": "Day 22",
      "pageStart": 0,
      "pageEnd": 0,
      "order": 19,
      "characterCount": 7099,
      "wordCount": 1465,
      "readTimeMinutes": 7
    },
    {
      "slug": "day-23-endless-horizon",
      "title": "Endless Horizon",
      "part": "Argentina",
      "day": "Day 23",
      "pageStart": 0,
      "pageEnd": 0,
      "order": 20,
      "characterCount": 1370,
      "wordCount": 267,
      "readTimeMinutes": 2
    },
    {
      "slug": "day-24-road-to-redemption",
      "title": "Road to Redemption",
      "part": "Argentina",
      "day": "Day 24",
      "pageStart": 0,
      "pageEnd": 0,
      "order": 21,
      "characterCount": 3907,
      "wordCount": 904,
      "readTimeMinutes": 5
    },
    {
      "slug": "day-25-crossing-the-border-on-a-bicycle",
      "title": "Crossing the Border on a Bicycle",
      "part": "Uruguay",
      "day": "Day 25",
      "pageStart": 0,
      "pageEnd": 0,
      "order": 22,
      "characterCount": 4062,
      "wordCount": 830,
      "readTimeMinutes": 4
    },
    {
      "slug": "day-26-unexpected-turns",
      "title": "Unexpected Turns",
      "part": "Uruguay",
      "day": "Day 26",
      "pageStart": 0,
      "pageEnd": 0,
      "order": 23,
      "characterCount": 3377,
      "wordCount": 752,
      "readTimeMinutes": 4
    },
    {
      "slug": "day-27-parting-ways-with-eduardo",
      "title": "Parting Ways with Eduardo",
      "part": "Uruguay",
      "day": "Day 27",
      "pageStart": 0,
      "pageEnd": 0,
      "order": 24,
      "characterCount": 3918,
      "wordCount": 802,
      "readTimeMinutes": 4
    },
    {
      "slug": "day-28-montevideo",
      "title": "Montevideo",
      "part": "Uruguay",
      "day": "Day 28",
      "pageStart": 0,
      "pageEnd": 0,
      "order": 25,
      "characterCount": 3499,
      "wordCount": 735,
      "readTimeMinutes": 4
    },
    {
      "slug": "day-29-lost-wheels",
      "title": "Lost Wheels",
      "part": "Uruguay",
      "day": "Day 29",
      "pageStart": 0,
      "pageEnd": 0,
      "order": 26,
      "characterCount": 4830,
      "wordCount": 1015,
      "readTimeMinutes": 5
    },
    {
      "slug": "day-30-shadow-and-i",
      "title": "Shadow and I",
      "part": "Uruguay",
      "day": "Day 30",
      "pageStart": 0,
      "pageEnd": 0,
      "order": 27,
      "characterCount": 2428,
      "wordCount": 524,
      "readTimeMinutes": 3
    },
    {
      "slug": "day-31-the-kindness-of-strangers",
      "title": "The Kindness of Strangers",
      "part": "Uruguay",
      "day": "Day 31",
      "pageStart": 0,
      "pageEnd": 0,
      "order": 28,
      "characterCount": 5485,
      "wordCount": 1180,
      "readTimeMinutes": 6
    },
    {
      "slug": "day-32-a-respite",
      "title": "A Respite",
      "part": "Uruguay",
      "day": "Day 32",
      "pageStart": 0,
      "pageEnd": 0,
      "order": 29,
      "characterCount": 1712,
      "wordCount": 381,
      "readTimeMinutes": 2
    },
    {
      "slug": "day-34-walk-again",
      "title": "Walk Again",
      "part": "Uruguay",
      "day": "Day 34",
      "pageStart": 0,
      "pageEnd": 0,
      "order": 30,
      "characterCount": 4315,
      "wordCount": 917,
      "readTimeMinutes": 5
    },
    {
      "slug": "day-35-crossing-another-border-on-foot",
      "title": "Crossing Another Border on Foot",
      "part": "Brazil",
      "day": "Day 35",
      "pageStart": 0,
      "pageEnd": 0,
      "order": 31,
      "characterCount": 6323,
      "wordCount": 1321,
      "readTimeMinutes": 7
    },
    {
      "slug": "day-36-the-albergue",
      "title": "The Albergue",
      "part": "Brazil",
      "day": "Day 36",
      "pageStart": 0,
      "pageEnd": 0,
      "order": 32,
      "characterCount": 4515,
      "wordCount": 960,
      "readTimeMinutes": 5
    },
    {
      "slug": "day-37-the-stray-and-the-wanderer",
      "title": "The Stray and the Wanderer",
      "part": "Brazil",
      "day": "Day 37",
      "pageStart": 0,
      "pageEnd": 0,
      "order": 33,
      "characterCount": 6442,
      "wordCount": 1380,
      "readTimeMinutes": 7
    },
    {
      "slug": "day-38-juliano-and-marcozi",
      "title": "Juliano and Marcozi",
      "part": "Brazil",
      "day": "Day 38",
      "pageStart": 0,
      "pageEnd": 0,
      "order": 34,
      "characterCount": 4272,
      "wordCount": 884,
      "readTimeMinutes": 5
    },
    {
      "slug": "day-39-unveiling-layers",
      "title": "Unveiling Layers",
      "part": "Brazil",
      "day": "Day 39",
      "pageStart": 0,
      "pageEnd": 0,
      "order": 35,
      "characterCount": 2352,
      "wordCount": 488,
      "readTimeMinutes": 3
    },
    {
      "slug": "day-40-paths-diverging-yet-converging",
      "title": "Paths Diverging Yet Converging",
      "part": "Brazil",
      "day": "Day 40",
      "pageStart": 0,
      "pageEnd": 0,
      "order": 36,
      "characterCount": 2340,
      "wordCount": 482,
      "readTimeMinutes": 3
    },
    {
      "slug": "day-41-the-fork-in-our-paths",
      "title": "The Fork in Our Paths",
      "part": "Brazil",
      "day": "Day 41",
      "pageStart": 0,
      "pageEnd": 0,
      "order": 37,
      "characterCount": 4425,
      "wordCount": 903,
      "readTimeMinutes": 5
    },
    {
      "slug": "day-42-whispers-of-the-wind",
      "title": "Whispers of the Wind",
      "part": "Brazil",
      "day": "Day 42",
      "pageStart": 0,
      "pageEnd": 0,
      "order": 38,
      "characterCount": 4289,
      "wordCount": 915,
      "readTimeMinutes": 5
    },
    {
      "slug": "day-43-through-rain-and-resolve",
      "title": "Through Rain and Resolve",
      "part": "Brazil",
      "day": "Day 43",
      "pageStart": 0,
      "pageEnd": 0,
      "order": 39,
      "characterCount": 3762,
      "wordCount": 808,
      "readTimeMinutes": 4
    },
    {
      "slug": "day-44-a-turn-of-fortune",
      "title": "A Turn of Fortune",
      "part": "Brazil",
      "day": "Day 44",
      "pageStart": 0,
      "pageEnd": 0,
      "order": 40,
      "characterCount": 4391,
      "wordCount": 878,
      "readTimeMinutes": 4
    },
    {
      "slug": "day-45-the-road-to-sao-paulo",
      "title": "The Road to São Paulo",
      "part": "Brazil",
      "day": "Day 45",
      "pageStart": 0,
      "pageEnd": 0,
      "order": 41,
      "characterCount": 6875,
      "wordCount": 1400,
      "readTimeMinutes": 7
    },
    {
      "slug": "day-46-the-journey-within",
      "title": "The Journey Within",
      "part": "Brazil",
      "day": "Day 46",
      "pageStart": 0,
      "pageEnd": 0,
      "order": 42,
      "characterCount": 1656,
      "wordCount": 348,
      "readTimeMinutes": 2
    }
  ],
  "coverage": "full"
}
